bluer_plugin/__init__.py
bluer_plugin/__main__.py
bluer_plugin/config.env
bluer_plugin/env.py
bluer_plugin/functions.py
bluer_plugin/host.py
bluer_plugin/logger.py
bluer_plugin/sample.env
bluer_plugin/urls.py
bluer_plugin/.abcli/abcli.sh
bluer_plugin/.abcli/actions.sh
bluer_plugin/.abcli/aka.sh
bluer_plugin/.abcli/alias.sh
bluer_plugin/.abcli/bluer_plugin.sh
bluer_plugin/.abcli/install.sh
bluer_plugin/.abcli/leaf.sh
bluer_plugin/.abcli/node.sh
bluer_plugin/.abcli/node/leaf.sh
bluer_plugin/.abcli/tests/README.sh
bluer_plugin/.abcli/tests/help.sh
bluer_plugin/.abcli/tests/thing.sh
bluer_plugin/.abcli/tests/thing_with_args.sh
bluer_plugin/.abcli/tests/version.sh
bluer_plugin/README/aliases.py
bluer_plugin/README/build.py
bluer_plugin/README/docs.py
bluer_plugin/README/feature_1.py
bluer_plugin/README/feature_2.py
bluer_plugin/README/feature_3.py
bluer_plugin/README/items.py
bluer_plugin/help/__init__.py
bluer_plugin/help/__main__.py
bluer_plugin/help/functions.py
bluer_plugin/help/node/__init__.py
bluer_plugin/help/node/functions.py
bluer_plugin/node/__init__.py
bluer_plugin/node/__main__.py
bluer_plugin/node/functions.py
bluer_plugin-4.62.1.dist-info/licenses/LICENSE
bluer_plugin-4.62.1.dist-info/METADATA
bluer_plugin-4.62.1.dist-info/WHEEL
bluer_plugin-4.62.1.dist-info/top_level.txt
bluer_plugin-4.62.1.dist-info/RECORD
